MANIFEST.in
README.md
pyproject.toml
src/mkdocs_nfdi4culture.egg-info/PKG-INFO
src/mkdocs_nfdi4culture.egg-info/SOURCES.txt
src/mkdocs_nfdi4culture.egg-info/dependency_links.txt
src/mkdocs_nfdi4culture.egg-info/entry_points.txt
src/mkdocs_nfdi4culture.egg-info/requires.txt
src/mkdocs_nfdi4culture.egg-info/top_level.txt
src/plugins/__init__.py
src/templates/404.html
src/templates/__init__.py
src/templates/base.html
src/templates/main.html
src/templates/mkdocs_theme.yml
src/templates/search.html
src/templates/__pycache__/__init__.cpython-311.pyc
src/templates/assets-compiled/css/n4c.css
src/templates/assets-compiled/fonts/Inter-Bold.woff2
src/templates/assets-compiled/fonts/Inter-Regular.woff2
src/templates/assets-compiled/fonts/Inter-SemiBold.woff2
src/templates/assets-compiled/images/clippy.svg
src/templates/assets-compiled/images/favicon.png
src/templates/assets-compiled/images/n4c-logo-black.svg
src/templates/assets-compiled/images/n4c-logo-white.svg
src/templates/assets-compiled/js/n4c.js
src/templates/assets-compiled/webfonts/fa-brands-400.ttf
src/templates/assets-compiled/webfonts/fa-brands-400.woff2
src/templates/assets-compiled/webfonts/fa-regular-400.ttf
src/templates/assets-compiled/webfonts/fa-regular-400.woff2
src/templates/assets-compiled/webfonts/fa-solid-900.ttf
src/templates/assets-compiled/webfonts/fa-solid-900.woff2
src/templates/assets-compiled/webfonts/fa-v4compatibility.ttf
src/templates/assets-compiled/webfonts/fa-v4compatibility.woff2
src/templates/partials/footer.html
src/templates/partials/search.html
src/templates/partials/sidebar.html